pyas/__init__.py
pyas-1.2.4.dist-info/LICENSE
pyas-1.2.4.dist-info/METADATA
pyas-1.2.4.dist-info/WHEEL
pyas-1.2.4.dist-info/top_level.txt
pyas-1.2.4.dist-info/RECORD
