Metadata-Version: 2.1
Name: pyas
Version: 1.2.4
Summary: Run machine code, assembly and webassembly directly in Python
Home-page: https://github.com/donno2048/pyas
Author: Elisha Hollander
Author-email: just4now666666@gmail.com
License: MIT
Project-URL: Documentation, https://github.com/donno2048/pyas#readme
Project-URL: Bug Reports, https://github.com/donno2048/pyas/issues
Project-URL: Source Code, https://github.com/donno2048/pyas
Platform: linux
Platform: emscripten
License-File: LICENSE
